[
  {"author": "マザー・テレサ", "quote": "愛は与えるほどに満たされる泉です。小さな愛から、世界は大きく変わります。"},
  {"author": "アルベルト・アインシュタイン", "quote": "人生は自転車に乗るようなもの。バランスを保つには、進み続けなければならない。"},
  {"author": "ヘレン・ケラー", "quote": "幸福は光の中にだけあるのではない。暗闇の中にも、希望の種は隠されている。"},
  {"author": "旅する心理学者ソフィア", "quote": "あなたの心は広大な宇宙。その中に、無限の可能性と輝きを秘めていることを忘れないでください。"},
  {"author": "ネルソン・マンデラ", "quote": "困難は私たちを打ち砕くのではなく、その中に秘められた強さを引き出すためにある。"},
  {"author": "レオナルド・ダ・ヴィンチ", "quote": "経験は最高の教師。失敗を恐れず、好奇心を持って学び続けなさい。"},
  {"author": "ドクター・セレスト", "quote": "星が夜空を照らすように、あなたの存在も誰かの道を明るく照らしています。"},
  {"author": "アンネ・フランク", "quote": "どんな小さな希望も、心の奥底で大切に育んでいれば、必ず未来を照らす光となる。"},
  {"author": "孔子", "quote": "過去は変えられないが、未来は今この瞬間の行動で築かれる。今日を大切にせよ。"},
  {"author": "ガンディー", "quote": "自らを変えることから始めなさい。そうすれば、世界もまたあなたに続くでしょう。"},
  {"author": "スティーブ・ジョブズ", "quote": "点と点がつながる瞬間を信じなさい。あなたの情熱が、いつか未来を拓くでしょう。"},
  {"author": "心の羅針盤ナビゲーター、アラン", "quote": "道に迷っても、心にはいつでも羅針盤がある。自分を信じて、進むべき方向を探そう。"},
  {"author": "オードリー・ヘプバーン", "quote": "美しさは内面から輝くもの。笑顔と優しさが、あなたを最も輝かせます。"},
  {"author": "マルティン・ルーサー・キング・ジュニア", "quote": "諦めない心こそが、最も強い武器です。希望を持ち続け、立ち上がりなさい。"},
  {"author": "宮沢賢治", "quote": "雨にも負けず、風にも負けぬ。心の強さこそが、あなたを支える光となる。"},
  {"author": "坂本龍馬", "quote": "世の中を変える力は、一人ひとりの心の中に宿る。恐れずに、新しい時代を創ろう。"},
  {"author": "エミリー・ディキンソン", "quote": "希望は翼を持った鳥。魂の中でさえずり、止まることなく、歌い続ける。"},
  {"author": "ヴィクトール・フランクル", "quote": "人生の意味は、私たちが困難にどう向き合うかによって見出されるものだ。"},
  {"author": "森の賢者エリカ", "quote": "自然がゆっくりと芽吹くように、あなたの心もまた、穏やかに成長しているのです。"},
  {"author": "アリストテレス", "quote": "幸福は行動にある。今日できることを精一杯行い、小さな喜びを見つけよう。"},
  {"author": "マリー・キュリー", "quote": "何事も恐れることはない。理解すること、それが大切。心を開いて探求しなさい。"},
  {"author": "夢見る探求者レオ", "quote": "夢は心に描く未来地図。恐れずに一歩踏み出せば、必ず道は開かれるでしょう。"},
  {"author": "フロイト", "quote": "過去は現在のあなたを形作るが、未来はあなたが今どう生きるかで決まる。"},
  {"author": "ユング", "quote": "自分自身を見つける旅は、最も偉大な冒険。内なる声に耳を傾けなさい。"},
  {"author": "作家：夏目漱石", "quote": "焦らず、弛まず。一歩一歩が、やがて大きな道となる。自分を信じて進め。"},
  {"author": "心と旅する詩人、アミ", "quote": "人生は美しい物語。辛い章があっても、それは次への序章に過ぎないのです。"},
  {"author": "デール・カーネギー", "quote": "今日という日は、二度と来ない贈り物。その一日を最高の笑顔で迎えよう。"},
  {"author": "歴史家：ユヴァル・ノア・ハラリ", "quote": "変化は避けられない。しかし、変化の中で自分を見失わない知恵があなたにはある。"},
  {"author": "旅の哲学者、カイ", "quote": "迷い道もまた、新たな発見の道。立ち止まって、心の声に耳を傾けてみよう。"},
  {"author": "フランツ・カフカ", "quote": "あなた自身の内なる光を見つけなさい。それが、暗闇を照らす唯一の道だ。"},
  {"author": "芸術家：フィンセント・ファン・ゴッホ", "quote": "夜空の星のように、あなたの個性は唯一無二の輝き。それを大切にしよう。"},
  {"author": "心のセラピスト、クレア", "quote": "涙は心の浄化の雨。泣きたいときは我慢せず、感情を解き放っていいのです。"},
  {"author": "詩人：谷川俊太郎", "quote": "ささやかな日々にこそ、無限の喜びが隠されている。その美しさに気づこう。"},
  {"author": "歴史上の哲学者、セネカ", "quote": "時間は有限な贈り物。今日という日を、後悔なく生きる勇気を持ちなさい。"},
  {"author": "探求者：アメリア・イヤハート", "quote": "困難の先にこそ、真の自由が待っている。恐れずに、新たな高みを目指そう。"},
  {"author": "星見の心理学者レオン", "quote": "あなたの心は小さな宇宙。どんな嵐が来ても、必ず晴れ間が訪れるでしょう。"},
  {"author": "作家：トルストイ", "quote": "愛は人生の光。与えるほどに、あなた自身の心も温かく満たされていく。"},
  {"author": "教育者：福沢諭吉", "quote": "学ぶことをやめなければ、成長もまた止まらない。常に前向きな心でいよう。"},
  {"author": "心のコンパス、ナビゲーター・リサ", "quote": "不安な時は、深呼吸。心の中のコンパスが、あなたを正しい方向へ導きます。"},
  {"author": "古代の賢者、ソクラテス", "quote": "自分を知ることから、すべての智慧は始まる。内なる声に耳を傾けなさい。"},
  {"author": "動物学者：ジェーン・グドール", "quote": "地球上のすべての命はつながっている。小さな行動も、大きな変化を生む力がある。"},
  {"author": "旅の吟遊詩人、ユリア", "quote": "過ぎ去りし日々は記憶の歌。未来はまだ歌われていない、あなただけの旋律です。"},
  {"author": "精神科医：河合隼雄", "quote": "心の闇もまた、あなたの一部。それを受け入れることで、新たな光が見える。"},
  {"author": "慈善家：フローレンス・ナイチンゲール", "quote": "奉仕の心は、最も美しい光。あなたの優しさが、誰かの心を癒やすでしょう。"},
  {"author": "心の庭師、リリー", "quote": "心の庭には、たくさんの種が眠っている。水を与えれば、美しい花を咲かせるでしょう。"},
  {"author": "政治家：ウィンストン・チャーチル", "quote": "成功は最終ではないし、失敗は致命的でもない。大切なのは、続ける勇気だ。"},
  {"author": "物理学者：マクスウェル", "quote": "真実は探求の果てにある。しかし、その過程で得るものこそが、人生を豊かにする。"},
  {"author": "共感の心理学者、エマ", "quote": "誰もが孤独を感じる瞬間がある。でも、あなたは一人じゃない。私がここにいます。"},
  {"author": "作家：太宰治", "quote": "人は皆、それぞれに美しい。自分を卑下することなく、その輝きを大切にしよう。"},
  {"author": "発明家：トーマス・エジソン", "quote": "失敗は成功のもと。諦めずに試行錯誤する心が、未来の扉を開く鍵となる。"},
  {"author": "瞑想の導師、ゼン", "quote": "静寂の中にこそ、心の答えがある。今日一日、ほんの少しの時間、立ち止まろう。"},
  {"author": "哲学者：パスカル", "quote": "人間は考える葦である。思考を通じて、あなたは無限の可能性を秘めている。"},
  {"author": "写真家：アンセル・アダムス", "quote": "美しい瞬間は、いつでもあなたのそばにある。心の目でそれを見つけよう。"},
  {"author": "ポジティブ心理学者、ハル", "quote": "感謝の気持ちは、心の栄養。日々の小さな幸せに気づくことで、人生は豊かになる。"},
  {"author": "皇帝：マルクス・アウレリウス", "quote": "今この瞬間を大切に生きなさい。それが、あなたの人生を最高の物語にする秘訣だ。"},
  {"author": "海洋学者：ジャック・クストー", "quote": "未知の領域への探求は、心の冒険。恐れずに、新しい自分に出会う旅に出よう。"},
  {"author": "心の旅人、ソラ", "quote": "過去の傷も、未来への教訓。すべてはあなたを強くするための糧となるでしょう。"},
  {"author": "詩人：金子みすゞ", "quote": "みんなちがって、みんないい。あなたの個性は、この世界を彩る大切な色です。"},
  {"author": "冒険家：植村直己", "quote": "限界は心の中に存在する。一歩踏み出せば、想像を超える景色が広がっている。"},
  {"author": "心の探求者、イヴ", "quote": "自分の感情に寄り添う時間を持ちましょう。それが、心の声を聞く第一歩です。"},
  {"author": "作曲家：ベートーヴェン", "quote": "苦悩の中からこそ、真の喜びは生まれる。絶望の先に、希望の旋律が響く。"},
  {"author": "作家：村上春樹", "quote": "失われたものは戻らない。しかし、そこから学ぶことは、未来への光となる。"},
  {"author": "心の調律師、メロディ", "quote": "心がざわつく夜は、静かに呼吸を整えよう。心にも、穏やかなリズムがあるはず。"},
  {"author": "哲学者：ニーチェ", "quote": "あなたが自分自身になること。それが、人生の最も偉大な芸術である。"},
  {"author": "芸術家：パブロ・ピカソ", "quote": "創造性を恐れるな。あなた自身の感情を表現することが、最も美しい芸術だ。"},
  {"author": "癒やしの伝道師、リア", "quote": "完璧でなくていい。ただ、今日のあなた自身を受け入れ、労ってあげましょう。"},
  {"author": "物理学者：ホーキング", "quote": "生命がある限り、希望はある。宇宙の神秘のように、あなたの可能性も無限大だ。"},
  {"author": "作家：サン＝テグジュペリ", "quote": "本当に大切なものは、目に見えない。心の目で、真実を見つめなさい。"},
  {"author": "心の道しるべ、ガイド・ケン", "quote": "どんな小さな進歩も、確かな成長の証。自分を褒め、次の一歩へと繋げよう。"},
  {"author": "仏陀", "quote": "過去に囚われず、未来を恐れず。今この瞬間を、意識して生きなさい。"},
  {"author": "医師：野口英世", "quote": "努力は必ず報われる。諦めずに挑み続けることが、夢を現実にする力となる。"},
  {"author": "心の開拓者、ディーン", "quote": "新しい扉を開くのは勇気が必要。でも、その先には必ず、新しい景色が待っている。"},
  {"author": "画家：クロード・モネ", "quote": "光の移ろいのように、人生もまた変化する。その変化を楽しみ、美しさを見つけよう。"},
  {"author": "詩人：ゲーテ", "quote": "今日できることを明日へ延ばすな。今この瞬間が、あなたの未来を創るのだ。"},
  {"author": "心の避難所、アンナ", "quote": "疲れたら休んでいい。心と体は、休息があるからこそ、また前に進めるのです。"},
  {"author": "歴史上の哲学者、エピクテトス", "quote": "コントロールできないことにとらわれるな。できることに集中し、心を平和に保て。"},
  {"author": "教育者：ジョン・デューイ", "quote": "経験は最高の学び。失敗を恐れず、好奇心を持って新しいことに挑戦しよう。"},
  {"author": "心の案内人、ルカ", "quote": "孤独を感じる夜も、空には星が輝いている。あなたは一人じゃないことを思い出して。"},
  {"author": "作家：遠藤周作", "quote": "心の奥底には、必ず光がある。どんな時も、その光を信じ、生きる希望を持て。"},
  {"author": "科学者：ダーウィン", "quote": "変化に適応する者が生き残る。柔軟な心で、新しい状況を受け入れよう。"},
  {"author": "心の鏡、ミシェル", "quote": "あなたの内面は、そのまま外面に映し出される。自分を愛し、大切にしよう。"},
  {"author": "思想家：ジャン＝ジャック・ルソー", "quote": "自然に帰りなさい。素朴な心こそが、真の幸福を見つける鍵となるだろう。"},
  {"author": "宇宙飛行士：ニール・アームストロング", "quote": "小さな一歩が、大きな飛躍を生む。恐れずに、未知の世界へ踏み出そう。"},
  {"author": "心の探求家、ユウキ", "quote": "弱さを見せることは、強さの証。自分を許し、ありのままの自分を受け入れよう。"},
  {"author": "童話作家：ハンス・クリスチャン・アンデルセン", "quote": "どんな物語にも、希望の光は宿っている。あなたの物語も、きっと輝かしいものになる。"},
  {"author": "哲学者：キルケゴール", "quote": "選択はあなたの自由。後悔するより、一歩踏み出す勇気を選びなさい。"},
  {"author": "心の泉、エリン", "quote": "疲れた心は、静かな場所で癒やしましょう。あなたの内には、回復の泉がある。"},
  {"author": "武道家：宮本武蔵", "quote": "心は常に清明であれ。迷いを捨て、目の前のことに集中すれば道は開ける。"},
  {"author": "心理学者：カール・ロジャーズ", "quote": "ありのままの自分を受け入れる時、あなたは最も強く、最も美しく輝く。"},
  {"author": "心の案内人、リョウ", "quote": "焦る気持ちを手放し、ゆっくりと進もう。あなたのペースが、最善の道となる。"},
  {"author": "政治家：ジョン・F・ケネディ", "quote": "希望は私たちを前向きにする力。困難な時こそ、未来への夢を描きなさい。"},
  {"author": "作家：アガサ・クリスティ", "quote": "人生は謎解きのよう。でも、あなたは必ず答えを見つけ、次へと進めるはず。"},
  {"author": "心の灯台、アキラ", "quote": "暗闇の中でも、心の灯台は常に輝いている。自分を信じ、その光を頼りに進もう。"},
  {"author": "詩人：吉野弘", "quote": "言葉は心の橋。優しい言葉が、あなたと誰かの心を温かくつなぐでしょう。"},
  {"author": "心理学者：アルフレッド・アドラー", "quote": "劣等感は、成長への原動力となる。それを乗り越え、新しい自分に出会おう。"},
  {"author": "心のヒーラー、サラ", "quote": "今日一日、自分自身に優しくあれ。その優しさが、明日への活力となるでしょう。"}
]