[
  {"author": "セリーナ・マリー（心理学者）", "quote": "完璧でなくていい。今のあなたで十分美しい。そのままで愛される価値がある。"},
  {"author": "マルクス・アウレリウス", "quote": "心の平穏は、外界の出来事ではなく、あなたの内なる反応によって決まる。"},
  {"author": "Dr. エルヴィン・ルフト（心理学者）", "quote": "立ち止まる勇気も、前へ進む力になる。焦らず、心の充電を大切に。"},
  {"author": "マザー・テレサ", "quote": "小さな愛の行いが、世界を変える大きな力となる。あなたの一歩を信じて。"},
  {"author": "アキラ・ヤマモト（心理学者）", "quote": "過去は変えられなくても、未来はあなたの手の中にある。今日から新たな一歩を。"},
  {"author": "ヘレン・ケラー", "quote": "人生は、恐れることではなく、理解すべき神秘に満ちている。光を見つけよう。"},
  {"author": "レオナルド・ダ・ヴィンチ", "quote": "困難はあなたを強くする。乗り越えられない壁はないと信じなさい。"},
  {"author": "ソフィア・カマル（心理学者）", "quote": "疲れを感じたら、自然の音に身を委ねて心を休ませて。あなたは休む価値がある。"},
  {"author": "ガンジー", "quote": "あなた自身が、世界に変化をもたらす存在である。その力を信じなさい。"},
  {"author": "孔子", "quote": "過ちを犯すことは人間である。それを改めることを怠らないのが賢者である。"},
  {"author": "Dr. エルヴィン・ルフト（心理学者）", "quote": "自分の弱さも、あなたの個性の一部。それを受け入れて愛するとき、真の強さが生まれる。"},
  {"author": "ナイチンゲール", "quote": "心に希望の光を灯せば、どんな闇も照らせる。諦めない心が道を開く。"},
  {"author": "セリーナ・マリー（心理学者）", "quote": "他者の評価より、あなたの心の声に耳を傾けて。それが一番確かな道しるべです。"},
  {"author": "福沢諭吉", "quote": "天は人の上に人をつくらず、人の下に人をつくらず。誰もが輝く存在である。"},
  {"author": "Dr. エルヴィン・ルフト（心理学者）", "quote": "自分を許すとき、心は本当の自由を知る。過去に囚われず、今を生きよう。"},
  {"author": "アリストテレス", "quote": "幸福は活動の中にある。小さな喜びを見つけ、感謝の心で満たそう。"},
  {"author": "ソフィア・カマル（心理学者）", "quote": "嵐の後の空には、いつも虹がかかることを忘れないで。希望は必ず訪れる。"},
  {"author": "坂本龍馬", "quote": "おのれの道は、おのれで切り開くもの。前を向いて進む勇気を持て。"},
  {"author": "アキラ・ヤマモト（心理学者）", "quote": "今日という日は、二度と来ない贈り物。大切に味わい、心ゆくまで楽しもう。"},
  {"author": "宮沢賢治", "quote": "すべての物事には意味がある。見えない希望の光を信じて歩もう。"},
  {"author": "セリーナ・マリー（心理学者）", "quote": "完璧主義を手放して、心の余白を作りましょう。それが創造の源となる。"},
  {"author": "マルクス・アウレリウス", "quote": "未来を恐れるな。それはまだ来ていない。今、この瞬間に集中しなさい。"},
  {"author": "Dr. エルヴィン・ルフト（心理学者）", "quote": "あなたの心は、癒やしの力を持っている。自分自身を信じ、そっと抱きしめて。"},
  {"author": "マザー・テレサ", "quote": "愛は与えるほど増える。あなたの周りの人々を温かく包み込みましょう。"},
  {"author": "アキラ・ヤマモト（心理学者）", "quote": "失敗は終わりではない。新たな学びの始まりだ。勇気を持って再挑戦しよう。"},
  {"author": "ヘレン・ケラー", "quote": "逆境は成長の糧である。困難を乗り越えるたび、あなたは強くなる。"},
  {"author": "レオナルド・ダ・ヴィンチ", "quote": "学ぶことをやめない限り、あなたは生きている。好奇心を持ち続けよう。"},
  {"author": "ソフィア・カマル（心理学者）", "quote": "時には、何もしない贅沢を自分に許しましょう。心の平和が最優先です。"},
  {"author": "ガンジー", "quote": "真の強さは、争うことではなく、穏やかに道を切り拓くことにある。"},
  {"author": "孔子", "quote": "自分を知り、他人を知る者は、百戦危うからず。内省を怠るな。"},
  {"author": "Dr. エルヴィン・ルフト（心理学者）", "quote": "不安を感じるときは、深呼吸をして、今ここに意識を集中させましょう。"},
  {"author": "ナイチンゲール", "quote": "奉仕の心は、自分自身の魂をも癒やす。与える喜びを大切に。"},
  {"author": "セリーナ・マリー（心理学者）", "quote": "あなたの感情は、あなたの一部。良いも悪いもなく、ただ感じて受け入れて。"},
  {"author": "福沢諭吉", "quote": "独立自尊の精神を持って生きよ。自分自身の価値を信じなさい。"},
  {"author": "Dr. エルヴィン・ルフト（心理学者）", "quote": "小さな一歩が、やがて大きな道となる。信じて進めば、道は開かれる。"},
  {"author": "アリストテレス", "quote": "徳とは習慣である。良い習慣を積み重ね、より良い自分を築こう。"},
  {"author": "ソフィア・カマル（心理学者）", "quote": "人との繋がりは、心の栄養。感謝の気持ちを大切に育んでいきましょう。"},
  {"author": "坂本龍馬", "quote": "世の人はわれを何とも言わば言え。我がなすことはわれのみぞ知る。"},
  {"author": "アキラ・ヤマモト（心理学者）", "quote": "過去を悔やまず、未来を恐れず、今を精一杯生きよう。それが幸福への道。"},
  {"author": "宮沢賢治", "quote": "雨にも負けず、風にも負けず。どんな困難にも立ち向かう強さを持て。"},
  {"author": "セリーナ・マリー（心理学者）", "quote": "あなたの内なる光は、決して消えることはない。信じて輝かせましょう。"},
  {"author": "マルクス・アウレリウス", "quote": "何事も自然の法則に従って起こる。それを受け入れ、平和を見出そう。"},
  {"author": "Dr. エルヴィン・ルフト（心理学者）", "quote": "あなたの心は、広大な宇宙。無限の可能性と安らぎがそこに広がる。"},
  {"author": "マザー・テレサ", "quote": "愛は家で始まる。家族への感謝と愛情を忘れずに。"},
  {"author": "アキラ・ヤマモト（心理学者）", "quote": "疲れたときは、空を見上げて深呼吸。大自然があなたを癒やしてくれる。"},
  {"author": "ヘレン・ケラー", "quote": "幸福の扉が一つ閉まると、別の扉が開く。希望を失わないで。"},
  {"author": "レオナルド・ダ・ヴィンチ", "quote": "知覚は知識の源である。五感を研ぎ澄まし、世界を深く感じよう。"},
  {"author": "ソフィア・カマル（心理学者）", "quote": "比較することなく、あなたのペースで進みましょう。誰もが唯一無二の存在。"},
  {"author": "ガンジー", "quote": "目には目を、歯には歯を、では世界中が盲目になってしまう。許しを選ぼう。"},
  {"author": "孔子", "quote": "知者は惑わず、仁者は憂えず、勇者は恐れず。心を鍛え、強くあれ。"},
  {"author": "Dr. エルヴィン・ルフト（心理学者）", "quote": "あなたの価値は、誰かの評価で決まるものではない。自分を信じて。"},
  {"author": "ナイチンゲール", "quote": "どんな困難な状況でも、希望の光は必ず見つかる。前向きな心で。"},
  {"author": "セリーナ・マリー（心理学者）", "quote": "心の声に耳を傾けて。それがあなたの真の望みを教えてくれる。"},
  {"author": "福沢諭吉", "quote": "学問は身を助ける。学び続けることで、あなたの世界は広がる。"},
  {"author": "Dr. エルヴィン・ルフト（心理学者）", "quote": "感情は波のように移り変わるもの。静かに観察し、流れるに任せましょう。"},
  {"author": "アリストテレス", "quote": "友は第二の自分である。良き友はあなたの人生を豊かにする。"},
  {"author": "ソフィア・カマル（心理学者）", "quote": "困難は一時的。あなたの回復力を信じ、乗り越える力を育てましょう。"},
  {"author": "坂本龍馬", "quote": "世の中に、無駄なものなど一つもない。すべての経験が財産となる。"},
  {"author": "アキラ・ヤマモト（心理学者）", "quote": "心の羅針盤は、いつもあなたの中にある。迷った時は、静かに内省を。"},
  {"author": "宮沢賢治", "quote": "私という現象は、仮定された有機交流電燈のひとつの青い照明です。"},
  {"author": "セリーナ・マリー（心理学者）", "quote": "自分自身への優しさを忘れないで。あなたは、あなたの一番の味方。"},
  {"author": "マルクス・アウレリウス", "quote": "怒りや悲しみに囚われるな。それらはあなた自身を傷つけるだけだ。"},
  {"author": "Dr. エルヴィン・ルフト（心理学者）", "quote": "感謝の心を持つことで、日常の中に多くの幸せを見つけられる。"},
  {"author": "マザー・テレサ", "quote": "私たちにできることは、大海の一滴にすぎない。されどその一滴は重要である。"},
  {"author": "アキラ・ヤマモト（心理学者）", "quote": "完璧を目指すのではなく、最善を尽くすことを心がけよう。それで十分だ。"},
  {"author": "ヘレン・ケラー", "quote": "私たちは、人生がどんなに困難でも、希望を捨ててはならない。"},
  {"author": "レオナルド・ダ・ヴィンチ", "quote": "観察はすべての知識の基礎である。細部に目を向け、深く洞察しよう。"},
  {"author": "ソフィア・カマル（心理学者）", "quote": "心配事を手放し、今できることに集中しましょう。あなたの力は無限大。"},
  {"author": "ガンジー", "quote": "非暴力は最強の武器である。愛と平和の心で世界を変えよう。"},
  {"author": "孔子", "quote": "己の欲せざる所は、人に施すこと勿れ。思いやりを大切に。"},
  {"author": "Dr. エルヴィン・ルフト（心理学者）", "quote": "心に栄養を与える時間を作りましょう。読書、音楽、静かな瞑想も良い。"},
  {"author": "ナイチンゲール", "quote": "癒やしは、心と体の両方から生まれる。バランスの取れた生活を。"},
  {"author": "セリーナ・マリー（心理学者）", "quote": "孤独を感じるときも、あなたは一人ではない。見えない繋がりを信じて。"},
  {"author": "福沢諭吉", "quote": "独立の気力なき者は、国を思うこと能わず。自分を律する力を養え。"},
  {"author": "Dr. エルヴィン・ルフト（心理学者）", "quote": "あなたの心は、あなただけの聖域。誰にも侵されない場所を守りましょう。"},
  {"author": "アリストテレス", "quote": "友を求める者は、友を作る価値のある人間にならなければならない。"},
  {"author": "ソフィア・カマル（心理学者）", "quote": "自然の中に身を置くことで、心のバランスが整い、癒やしが訪れます。"},
  {"author": "坂本龍馬", "quote": "人の世に道は一つということはない。二つも三つもある。自分の道を見つけよう。"},
  {"author": "アキラ・ヤマモト（心理学者）", "quote": "どんな小さな進歩も祝おう。それが、次のステップへの原動力となる。"},
  {"author": "宮沢賢治", "quote": "ほんとうの幸いは一体なんだろう。自分で探し、自分で見つけ出そう。"},
  {"author": "セリーナ・マリー（心理学者）", "quote": "あなたの笑顔は、周りの人々をも温かく照らす。笑顔を大切に。"},
  {"author": "マルクス・アウレリウス", "quote": "人生は変化そのものである。変化を受け入れ、それに適応しなさい。"},
  {"author": "Dr. エルヴィン・ルフト（心理学者）", "quote": "自分自身を大切にすることは、わがままではない。心身の健康があってこそ。"},
  {"author": "マザー・テレサ", "quote": "平和の祈りは微笑みから始まる。あなたの笑顔で平和を広げよう。"},
  {"author": "アキラ・ヤマモト（心理学者）", "quote": "諦めない心が、道を切り開く。あなたにはその力がある。"},
  {"author": "ヘレン・ケラー", "quote": "最も悲しいことは、目が見えるのに、ビジョンを持たないことだ。"},
  {"author": "レオナルド・ダ・ヴィンチ", "quote": "経験は知識の母である。実践を通じて学び、成長しよう。"},
  {"author": "ソフィア・カマル（心理学者）", "quote": "あなたは一人ではない。困ったときは、頼れる人に助けを求めましょう。"},
  {"author": "ガンジー", "quote": "信仰とは、論理では届かない場所まで、物事を信じることだ。"},
  {"author": "孔子", "quote": "学びて思わざれば則ち罔し。思いて学ばざれば則ち殆し。深く考察せよ。"},
  {"author": "Dr. エルヴィン・ルフト（心理学者）", "quote": "あなたの呼吸は、今ここに生きている証。深く吸い込み、心を落ち着かせよう。"},
  {"author": "ナイチンゲール", "quote": "真の強さは、優しさの中にある。弱き者に寄り添う心を忘れずに。"},
  {"author": "セリーナ・マリー（心理学者）", "quote": "あなたの人生は、あなただけの物語。自分らしく、最高の章を書き続けよう。"},
  {"author": "福沢諭吉", "quote": "人の言論は重きもの。自分の言葉に責任を持ち、真実を語れ。"},
  {"author": "Dr. エルヴィン・ルフト（心理学者）", "quote": "過去の過ちにとらわれず、新たな視点を持つことで、道は開ける。"},
  {"author": "アリストテレス", "quote": "知識とは、魂にとって最高の善である。学びを追求し続けなさい。"},
  {"author": "ソフィア・カマル（心理学者）", "quote": "心の奥底にある、あなたの真の願いに耳を傾けて。それが進むべき道を示す。"},
  {"author": "坂本龍馬", "quote": "事をなすには、まず心を動かすべし。情熱が道を切り開く。"},
  {"author": "アキラ・ヤマモト（心理学者）", "quote": "毎朝、自分に「大丈夫」と語りかけよう。その言葉が力となる。"},
  {"author": "宮沢賢治", "quote": "世界がぜんたい幸福にならないうちは、個人の幸福はありえない。"},
  {"author": "セリーナ・マリー（心理学者）", "quote": "あなたの心には、無限の愛と慈悲が宿っている。それを解き放ちましょう。"}
]