[
  {"author": "マルクス・アウレリウス", "quote": "今日の苦難も、明日の糧となる。心に平静を保ち、強くあれ。"},
  {"author": "マザー・テレサ", "quote": "愛は小さな行いの中に宿る。心からの優しさが世界を変える。"},
  {"author": "レオナルド・ダ・ヴィンチ", "quote": "好奇心を忘れずに、常に学び続けよう。そこに無限の可能性が眠る。"},
  {"author": "ガンディー", "quote": "自らが望む変化に、まず君自身がなろう。小さな一歩が未来を創る。"},
  {"author": "孔子", "quote": "過ちを恐れるな。そこから学ぶことができれば、それは進歩だ。"},
  {"author": "ヘレン・ケラー", "quote": "希望は目に見えずとも、心に光を灯す。信じる力を大切にしよう。"},
  {"author": "宮沢賢治", "quote": "雨にも負けず、風にも負けず。強くしなやかな心が、君を支える。"},
  {"author": "空海", "quote": "心に灯された一筋の光は、やがて闇を照らす大いなる智慧となる。"},
  {"author": "アンネ・フランク", "quote": "どんな困難の中にも、美しさと希望を見つける心を失わないで。"},
  {"author": "アインシュタイン", "quote": "想像力は知識よりも大切だ。無限の宇宙を心に描いてみよう。"},
  {"author": "エマーソン", "quote": "自分自身の声に耳を傾けよう。内なる真実が君を導くだろう。"},
  {"author": "セネカ", "quote": "幸福は外ではなく、君の内にある。今あるものに感謝しよう。"},
  {"author": "ソクラテス", "quote": "無知を認めることから、真の知恵は始まる。常に問い続けよう。"},
  {"author": "プラトン", "quote": "理想を高く掲げ、その光に向かって進め。君の心はそれを知っている。"},
  {"author": "星の旅人ゾルバ", "quote": "旅路で出会うすべての縁を大切に。それが君の魂の輝きとなる。"},
  {"author": "森の賢者エリオット", "quote": "自然の営みは、焦らず待つことを教えてくれる。心穏やかに進もう。"},
  {"author": "時の紡ぎ手ラヴィ", "quote": "過去は変えられずとも、未来は創れる。今日の選択が明日を織りなす。"},
  {"author": "心の地図職人アリス", "quote": "君の心の地図には、まだ見ぬ宝が隠されている。冒険を恐れるな。"},
  {"author": "夢見る航海士カイ", "quote": "荒波も追い風に変えよう。夢という名の帆を高く掲げて進め。"},
  {"author": "風の吟遊詩人リュン", "quote": "風の歌に耳を傾けてごらん。そこには自由と癒やしの調べがある。"},
  {"author": "光の導き手セラフィナ", "quote": "暗闇の中でも、小さな光を見つけよう。それが希望への道標となる。"},
  {"author": "古の書物番アルバス", "quote": "歴史は語る、困難は乗り越えられると。君の内に秘めた力を信じよ。"},
  {"author": "静寂の庭師リーフ", "quote": "心に静寂という名の庭を育てよう。そこには安らぎと成長が宿る。"},
  {"author": "叡智の泉守クロノス", "quote": "時間は有限だが、学びは無限だ。一瞬一瞬を大切に生きよう。"},
  {"author": "希望の種まき人フローラ", "quote": "どんな小さな希望の種も、大切に育てれば、やがて大輪の花となる。"},
  {"author": "無限の空を見上げる者サミュエル", "quote": "空はいつも君を見守っている。悩みは小さく、可能性は無限大だ。"},
  {"author": "語り部のエルド", "quote": "君の物語はまだ始まったばかり。どんな困難も、次章への序章だ。"},
  {"author": "導きの風使いアリア", "quote": "迷った時は、心の風向きを感じてごらん。きっと正しい道を示す。"},
  {"author": "心の羅針盤ナディア", "quote": "君の心には、進むべき方向を示す羅針盤がある。その声を聞きなさい。"},
  {"author": "魂の旅人ゼノン", "quote": "人生は魂を磨く旅。経験すべてが、君を深く豊かな存在にする。"},
  {"author": "記憶の番人ミューズ", "quote": "悲しい記憶も、いつか宝物になる。乗り越えた証として輝くだろう。"},
  {"author": "未来の夢見人ルミナ", "quote": "夢見ることをやめないで。その輝きが、未来を明るく照らす光となる。"},
  {"author": "星屑の吟遊詩人オリオン", "quote": "星々が歌うように、君も自分の歌を奏でよう。その音色は美しい。"},
  {"author": "月の賢者セレネ", "quote": "闇夜に輝く月のように、君もまた、誰かの心をそっと照らす光となれる。"},
  {"author": "アリストテレス", "quote": "幸福は日々の行いの結果である。善き選択を積み重ね、豊かに生きよう。"},
  {"author": "ダーウィン", "quote": "変化を恐れず、適応する力を信じよう。進化こそが君を強くする。"},
  {"author": "ベートーヴェン", "quote": "逆境の中でこそ、魂の音色は響く。君の心のメロディを奏でよう。"},
  {"author": "ゴッホ", "quote": "星月夜のように、君の心にも輝きがある。その情熱を表現しよう。"},
  {"author": "モーツァルト", "quote": "人生は即興曲。予期せぬ展開も楽しんで、自由に音を奏でよう。"},
  {"author": "夏目漱石", "quote": "心の声に耳を傾け、自分らしく生きよう。それが一番の安らぎとなる。"},
  {"author": "与謝野晶子", "quote": "愛と美は、この世界を彩る力。心のままに、その輝きを謳歌しよう。"},
  {"author": "野口英世", "quote": "困難は偉大な発見の源だ。諦めずに挑戦する心が未来を拓く。"},
  {"author": "キュリー夫人", "quote": "たゆまぬ探求心が、未知の扉を開く。君の探求心を信じて進もう。"},
  {"author": "ナイチンゲール", "quote": "誰かの痛みに寄り添う心こそ、最も尊い光。優しさを忘れずに。"},
  {"author": "キング牧師", "quote": "夢は言葉から始まる。平和への願いを語り続け、行動に移そう。"},
  {"author": "織田信長", "quote": "常識を打ち破る勇気を持て。新たな時代は、君の挑戦から生まれる。"},
  {"author": "坂本龍馬", "quote": "未来は自分たちの手で創るもの。志を胸に、大海原へ漕ぎ出そう。"},
  {"author": "吉田松陰", "quote": "志あれば、道は開かれる。心の灯を絶やさず、学び続けよ。"},
  {"author": "渋沢栄一", "quote": "道徳と経済は両輪。正しい心で富を築けば、社会は豊かになる。"},
  {"author": "福沢諭吉", "quote": "学問は独立の道を開く。自ら学び、自ら考え、道を切り拓こう。"},
  {"author": "星の旅人ゾルバ", "quote": "見知らぬ道も、一歩踏み出せば新しい景色が広がる。恐れずに進め。"},
  {"author": "森の賢者エリオット", "quote": "大地に根を張る木のように、君もまた、困難に耐え成長できる。"},
  {"author": "時の紡ぎ手ラヴィ", "quote": "時は流れる水のごとし。過去に囚われず、今という流れを楽しもう。"},
  {"author": "心の地図職人アリス", "quote": "君の心の奥底には、まだ見ぬ才能が隠されている。自分を信じて。"},
  {"author": "夢見る航海士カイ", "quote": "どんなに遠い夢も、追い続ける限り、いつか岸辺に辿り着くだろう。"},
  {"author": "風の吟遊詩人リュン", "quote": "喜びも悲しみも、風に乗せて遠くへ。心はいつも自由であるべきだ。"},
  {"author": "光の導き手セラフィナ", "quote": "君自身の心が、最も明るい光。その輝きで、周りを照らしてあげよう。"},
  {"author": "古の書物番アルバス", "quote": "人生は一冊の書物。どんなページも意味がある。読み進める勇気を。"},
  {"author": "静寂の庭師リーフ", "quote": "心の雑草を抜き、美しい花を咲かせよう。内なる平和を見つけよう。"},
  {"author": "叡智の泉守クロノス", "quote": "一瞬の決断が、永遠を変えることもある。直感を信じ、前に進もう。"},
  {"author": "希望の種まき人フローラ", "quote": "世界はまだ、君の優しさを待っている。小さな行動で、希望を蒔こう。"},
  {"author": "無限の空を見上げる者サミュエル", "quote": "悩みはちっぽけな雲。やがて流れ去り、無限の青空が広がる。"},
  {"author": "語り部のエルド", "quote": "悲劇も喜劇も、人生の一部。すべての経験が君の物語を豊かにする。"},
  {"author": "導きの風使いアリア", "quote": "向かい風は、高く飛ぶための助走。恐れず、羽を広げてみよう。"},
  {"author": "心の羅針盤ナディア", "quote": "真の強さは、自分の弱さを知ることから。偽りのない心で進もう。"},
  {"author": "魂の旅人ゼノン", "quote": "君の魂は、無限の可能性を秘めている。自分を信じ、羽ばたこう。"},
  {"author": "記憶の番人ミューズ", "quote": "過ぎ去った日々は、君を形作った大切な記憶。すべてを受け入れよう。"},
  {"author": "未来の夢見人ルミナ", "quote": "未来は、君が描く夢の数だけ存在する。どんな夢も諦めないで。"},
  {"author": "星屑の吟遊詩人オリオン", "quote": "君の存在自体が、宇宙にとって奇跡。その輝きを大切にしよう。"},
  {"author": "月の賢者セレネ", "quote": "完璧でなくとも、君は美しい。その不完全さが、君の魅力なのだ。"},
  {"author": "アリストテレス", "quote": "勇気は恐れを知らぬことではない。恐れを乗り越える力のことだ。"},
  {"author": "マザー・テレサ", "quote": "小さな手助けが、誰かの心を温める。日々の善意を大切にしよう。"},
  {"author": "レオナルド・ダ・ヴィンチ", "quote": "知ることは感じることから始まる。五感を研ぎ澄ませ、世界を感じよう。"},
  {"author": "ガンディー", "quote": "真の力は、非暴力と愛の中にある。心の平和を追求しよう。"},
  {"author": "孔子", "quote": "君の最大の栄光は、決して倒れないことではない。倒れるたびに起き上がることだ。"},
  {"author": "ヘレン・ケラー", "quote": "人生は勇敢な冒険か、何もないかのどちらかだ。一歩踏み出そう。"},
  {"author": "宮沢賢治", "quote": "世界が君の優しさを待っている。心を込めて、精一杯生きよう。"},
  {"author": "空海", "quote": "迷いは心の霧。静かに呼吸し、澄んだ心で真実を見つめよう。"},
  {"author": "アンネ・フランク", "quote": "人間は常に成長する。明日を信じて、今日を精一杯生きよう。"},
  {"author": "アインシュタイン", "quote": "常識とは、18歳までに身につけた偏見のコレクションのことだ。自由に考えよう。"},
  {"author": "エマーソン", "quote": "君が信じるもの、それが君の真実となる。自分を深く信頼しよう。"},
  {"author": "セネカ", "quote": "幸福は富や名誉ではなく、心の満足にある。今ある幸せを見つけよう。"},
  {"author": "ソクラテス", "quote": "何よりも自分自身を知れ。その知識が、君を自由にするだろう。"},
  {"author": "プラトン", "quote": "美しさは、魂の響きから生まれる。内面の輝きを磨き続けよう。"},
  {"author": "星の旅人ゾルバ", "quote": "人生は短い。だからこそ、すべての瞬間を愛し、心ゆくまで楽しもう。"},
  {"author": "森の賢者エリオット", "quote": "大地は全てを受け入れる。君の悩みも、やがて土に還るだろう。"},
  {"author": "時の紡ぎ手ラヴィ", "quote": "未来への不安も、過去への後悔も、今を生きる力に変えよう。"},
  {"author": "心の地図職人アリス", "quote": "君だけの道を歩こう。誰かの足跡を追う必要はない。"},
  {"author": "夢見る航海士カイ", "quote": "たとえ嵐が来ても、星はいつもそこにある。希望の光を見失うな。"},
  {"author": "風の吟遊詩人リュン", "quote": "心に喜びの歌を。その調べが、どんな悲しみも癒やしてくれる。"},
  {"author": "光の導き手セラフィナ", "quote": "君の小さな一歩が、誰かの大きな光となる。その勇気を信じて。"},
  {"author": "古の書物番アルバス", "quote": "人生の答えは、君自身の内にある。静かに耳を傾け、見つけ出そう。"},
  {"author": "静寂の庭師リーフ", "quote": "休息は怠惰ではない。心と体を育むための大切な時間だ。"},
  {"author": "叡智の泉守クロノス", "quote": "すべての経験が、君を賢者へと導く。失敗も、成長の糧としよう。"},
  {"author": "希望の種まき人フローラ", "quote": "今日できる最善を尽くせば、必ず明日は花開く。信じて種を蒔こう。"},
  {"author": "無限の空を見上げる者サミュエル", "quote": "君の可能性は、この大空のように無限だ。限界を決めつけないで。"}
]